inumet_api/__init__.py
inumet_api/api.py
inumet_api-0.2.2.dist-info/METADATA
inumet_api-0.2.2.dist-info/WHEEL
inumet_api-0.2.2.dist-info/licenses/LICENSE
inumet_api-0.2.2.dist-info/RECORD
