Metadata-Version: 2.4
Name: inumet_api
Version: 0.2.2
Summary: INUMET Api wrapper for python
Project-URL: Homepage, https://github.com/aronkahrs-us/inumet-api
Project-URL: Issues, https://github.com/aronkahrs-us/inumet-api/issues
Author-email: Aron Kahrs <aronkahrs.us@gmail.com>
License-File: LICENSE
Classifier: License :: OSI Approved :: MIT License
Classifier: Operating System :: OS Independent
Classifier: Programming Language :: Python :: 3
Requires-Python: >=3.8
